ha_mcp/__init__.py
ha_mcp/__main__.py
ha_mcp/_pypi_marker
ha_mcp/config.py
ha_mcp/errors.py
ha_mcp/py.typed
ha_mcp/server.py
ha_mcp/smoke_test.py
ha_mcp/client/__init__.py
ha_mcp/client/rest_client.py
ha_mcp/client/websocket_client.py
ha_mcp/client/websocket_listener.py
ha_mcp/resources/card_types.json
ha_mcp/resources/dashboard_guide.md
ha_mcp/tools/__init__.py
ha_mcp/tools/backup.py
ha_mcp/tools/device_control.py
ha_mcp/tools/enhanced.py
ha_mcp/tools/helpers.py
ha_mcp/tools/registry.py
ha_mcp/tools/smart_search.py
ha_mcp/tools/tools_addons.py
ha_mcp/tools/tools_areas.py
ha_mcp/tools/tools_blueprints.py
ha_mcp/tools/tools_bug_report.py
ha_mcp/tools/tools_calendar.py
ha_mcp/tools/tools_camera.py
ha_mcp/tools/tools_config_automations.py
ha_mcp/tools/tools_config_dashboards.py
ha_mcp/tools/tools_config_helpers.py
ha_mcp/tools/tools_config_info.py
ha_mcp/tools/tools_config_scripts.py
ha_mcp/tools/tools_filesystem.py
ha_mcp/tools/tools_groups.py
ha_mcp/tools/tools_hacs.py
ha_mcp/tools/tools_history.py
ha_mcp/tools/tools_integrations.py
ha_mcp/tools/tools_labels.py
ha_mcp/tools/tools_mcp_component.py
ha_mcp/tools/tools_registry.py
ha_mcp/tools/tools_resources.py
ha_mcp/tools/tools_search.py
ha_mcp/tools/tools_service.py
ha_mcp/tools/tools_services.py
ha_mcp/tools/tools_system.py
ha_mcp/tools/tools_todo.py
ha_mcp/tools/tools_traces.py
ha_mcp/tools/tools_updates.py
ha_mcp/tools/tools_utility.py
ha_mcp/tools/tools_voice_assistant.py
ha_mcp/tools/tools_zones.py
ha_mcp/tools/util_helpers.py
ha_mcp/utils/__init__.py
ha_mcp/utils/domain_handlers.py
ha_mcp/utils/fuzzy_search.py
ha_mcp/utils/operation_manager.py
ha_mcp/utils/usage_logger.py
ha_mcp-5.0.6.dist-info/licenses/LICENSE
tests/__init__.py
tests/test_constants.py
tests/test_env_manager.py
ha_mcp-5.0.6.dist-info/METADATA
ha_mcp-5.0.6.dist-info/WHEEL
ha_mcp-5.0.6.dist-info/entry_points.txt
ha_mcp-5.0.6.dist-info/top_level.txt
ha_mcp-5.0.6.dist-info/RECORD
