Metadata-Version: 2.4
Name: ha-mcp
Version: 5.0.6
Summary: Home Assistant MCP Server - Complete control of Home Assistant through MCP
Author-email: Julien <github@qc-h.net>
License: MIT
Project-URL: Homepage, https://github.com/homeassistant-ai/ha-mcp
Project-URL: Bug Tracker, https://github.com/homeassistant-ai/ha-mcp/issues
Project-URL: Repository, https://github.com/homeassistant-ai/ha-mcp
Keywords: mcp,home-assistant,ai,automation,smart-home
Classifier: Development Status :: 5 - Production/Stable
Classifier: Intended Audience :: Developers
Classifier: License :: OSI Approved :: MIT License
Classifier: Programming Language :: Python :: 3
Classifier: Programming Language :: Python :: 3.13
Classifier: Topic :: Home Automation
Classifier: Topic :: Software Development :: Libraries :: Python Modules
Requires-Python: <3.14,>=3.13
License-File: LICENSE
Requires-Dist: fastmcp>=2.11.0
Requires-Dist: httpx>=0.27.0
Requires-Dist: jq>=1.8.0; sys_platform != "win32"
Requires-Dist: textdistance[extras]>=4.6.0; platform_machine != "arm64" and platform_machine != "aarch64" and platform_machine != "ARM64"
Requires-Dist: textdistance>=4.6.0; platform_machine == "arm64" or platform_machine == "aarch64" or platform_machine == "ARM64"
Requires-Dist: pydantic>=2.5.0
Requires-Dist: python-dotenv>=1.0.0
Requires-Dist: truststore>=0.10.0
Requires-Dist: websockets>=12.0
Dynamic: license-file
